capycli/__init__.py
capycli/__main__.py
capycli/bom/__init__.py
capycli/bom/bom_convert.py
capycli/bom/bom_package.py
capycli/bom/bom_validate.py
capycli/bom/check_bom.py
capycli/bom/check_bom_item_status.py
capycli/bom/check_granularity.py
capycli/bom/create_components.py
capycli/bom/csv.py
capycli/bom/diff_bom.py
capycli/bom/download_sources.py
capycli/bom/filter_bom.py
capycli/bom/findsources.py
capycli/bom/handle_bom.py
capycli/bom/html.py
capycli/bom/legacy.py
capycli/bom/legacy_cx.py
capycli/bom/map_bom.py
capycli/bom/merge_bom.py
capycli/bom/plaintext.py
capycli/bom/show_bom.py
capycli/common/__init__.py
capycli/common/capycli_bom_support.py
capycli/common/comparable_version.py
capycli/common/component_cache.py
capycli/common/dependencies_base.py
capycli/common/file_support.py
capycli/common/github_support.py
capycli/common/html_support.py
capycli/common/json_support.py
capycli/common/map_result.py
capycli/common/print.py
capycli/common/purl_service.py
capycli/common/purl_store.py
capycli/common/purl_utils.py
capycli/common/script_base.py
capycli/common/script_support.py
capycli/data/__init__.py
capycli/data/granularity_list.csv
capycli/dependencies/__init__.py
capycli/dependencies/handle_dependencies.py
capycli/dependencies/javascript.py
capycli/dependencies/maven_list.py
capycli/dependencies/maven_pom.py
capycli/dependencies/nuget.py
capycli/dependencies/python.py
capycli/dependencies/rust.py
capycli/main/__init__.py
capycli/main/application.py
capycli/main/argument_parser.py
capycli/main/cli.py
capycli/main/exceptions.py
capycli/main/options.py
capycli/main/result_codes.py
capycli/mapping/handle_mapping.py
capycli/mapping/mapping_to_html.py
capycli/mapping/mapping_to_xlsx.py
capycli/moverview/handle_moverview.py
capycli/moverview/moverview_to_html.py
capycli/moverview/moverview_to_xlsx.py
capycli/project/__init__.py
capycli/project/check_prerequisites.py
capycli/project/create_bom.py
capycli/project/create_project.py
capycli/project/create_readme.py
capycli-2.10.0.dist-info/entry_points.txt
capycli-2.10.0.dist-info/licenses/License.md
capycli-2.10.0.dist-info/METADATA
capycli-2.10.0.dist-info/WHEEL
capycli-2.10.0.dist-info/RECORD
