Metadata-Version: 2.4
Name: capycli
Version: 2.10.0
Summary: CaPyCli - Clearing Automation Python Command Line Interface for SW360
License-Expression: MIT
License-File: License.md
Keywords: sw360,cli, automation,license,compliance,clearing
Author: Thomas Graf
Author-email: thomas.graf@siemens.com
Requires-Python: >=3.11,<3.15
Classifier: Development Status :: 5 - Production/Stable
Classifier: Intended Audience :: Developers
Classifier: Natural Language :: English
Classifier: Operating System :: OS Independent
Classifier: Programming Language :: Python :: 3 :: Only
Requires-Dist: beautifulsoup4 (>=4.11.1,<5.0.0)
Requires-Dist: chardet (==5.2.0)
Requires-Dist: cli-support (==2.0.1)
Requires-Dist: colorama (>=0.4.3,<0.5.0)
Requires-Dist: cyclonedx-python-lib (>=11.4.0,<12.0.0)
Requires-Dist: dateparser (>=1.1.8,<2.0.0)
Requires-Dist: halo (>=0.0.31,<0.0.32)
Requires-Dist: importlib-resources (>=5.12.0,<6.0.0)
Requires-Dist: jsonschema (>=4.23.0,<5.0.0)
Requires-Dist: openpyxl (>=3.0.3,<4.0.0)
Requires-Dist: packageurl-python (>=0.15.6,<0.16.0)
Requires-Dist: pyjwt (>=2.4.0,<3.0.0)
Requires-Dist: requests (>=2.31.0,<3.0.0)
Requires-Dist: requirements-parser (==0.11.0)
Requires-Dist: semver (==3.0.2)
Requires-Dist: sw360 (>=1.8.1,<2.0.0)
Requires-Dist: urllib3 (>=2.5.0,<3.0.0)
Requires-Dist: validation (>=0.8.3,<0.9.0)
Requires-Dist: wheel (>=0.38.4,<0.39.0)
Project-URL: Homepage, https://github.com/sw360/capycli
Project-URL: Repository, https://github.com/sw360/capycli
Project-URL: issues, https://github.com/sw360/capycli/issues
